{
  "db_name": "workshop_paper",
  "nodes": [
    {
      "name": "workshop",
      "columns": [
        {
          "name": "Workshop_ID",
          "type": "INT"
        },
        {
          "name": "Date",
          "type": "TEXT"
        },
        {
          "name": "Venue",
          "type": "TEXT"
        },
        {
          "name": "Name",
          "type": "TEXT"
        }
      ],
      "pk": [
        "Workshop_ID"
      ]
    },
    {
      "name": "submission",
      "columns": [
        {
          "name": "Submission_ID",
          "type": "INT"
        },
        {
          "name": "Scores",
          "type": "REAL"
        },
        {
          "name": "Author",
          "type": "TEXT"
        },
        {
          "name": "College",
          "type": "TEXT"
        }
      ],
      "pk": [
        "Submission_ID"
      ]
    },
    {
      "name": "Acceptance",
      "columns": [
        {
          "name": "Submission_ID",
          "type": "INT"
        },
        {
          "name": "Workshop_ID",
          "type": "INT"
        },
        {
          "name": "Result",
          "type": "TEXT"
        }
      ],
      "pk": [
        "Submission_ID",
        "Workshop_ID"
      ]
    }
  ],
  "edges": [
    {
      "from": "Acceptance",
      "to": "workshop",
      "child_col": "Workshop_ID",
      "parent_col": "Workshop_ID"
    },
    {
      "from": "Acceptance",
      "to": "submission",
      "child_col": "Submission_ID",
      "parent_col": "Submission_ID"
    }
  ],
  "centrality": {
    "workshop": 0.5,
    "submission": 0.5,
    "Acceptance": 0.0
  }
}